PyOKNN/__init__.py
PyOKNN/core.py
PyOKNN/data/COLUMBUS/columbus.dbf
PyOKNN/data/COLUMBUS/columbus.html
PyOKNN/data/COLUMBUS/columbus.png
PyOKNN/data/COLUMBUS/columbus.shp
PyOKNN/data/COLUMBUS/columbus.shx
PyOKNN/data/COLUMBUS/columbus.txt
PyOKNN/data/COLUMBUS.out/.szd/_ER{0}AR{0}MA{0}-BT(10).ckl
PyOKNN/data/COLUMBUS.out/.szd/_ER{0}AR{0}MA{0}-BT(100).ckl
PyOKNN/data/COLUMBUS.out/.szd/_ER{0}AR{0}MA{0}-BT(1000).ckl
PyOKNN/data/COLUMBUS.out/.szd/_ER{0}AR{0}MA{0}-BT(10000).ckl
PyOKNN/data/COLUMBUS.out/.szd/_ER{0}AR{0}MA{0}-BT(50).ckl
PyOKNN/data/COLUMBUS.out/.szd/_ER{0}AR{0}MA{0}-JK.ckl
PyOKNN/data/COLUMBUS.out/.szd/columbus_DMat_[full].ckl
PyOKNN/data/COLUMBUS.out/.szd/columbus_SMat_[full].ckl
PyOKNN/data/COLUMBUS.out/.szd/w_o0nn_matrix_as_arr.ckl
PyOKNN/data/COLUMBUS.out/.szd/w_o10nn_matrix_as_psw.ckl
PyOKNN/data/COLUMBUS.out/.szd/w_o11nn_matrix_as_psw.ckl
PyOKNN/data/COLUMBUS.out/.szd/w_o12nn_matrix_as_arr.ckl
PyOKNN/data/COLUMBUS.out/.szd/w_o12nn_matrix_as_psw.ckl
PyOKNN/data/COLUMBUS.out/.szd/w_o13nn_matrix_as_psw.ckl
PyOKNN/data/COLUMBUS.out/.szd/w_o14nn_matrix_as_psw.ckl
PyOKNN/data/COLUMBUS.out/.szd/w_o15nn_matrix_as_psw.ckl
PyOKNN/data/COLUMBUS.out/.szd/w_o16nn_matrix_as_psw.ckl
PyOKNN/data/COLUMBUS.out/.szd/w_o17nn_matrix_as_psw.ckl
PyOKNN/data/COLUMBUS.out/.szd/w_o18nn_matrix_as_psw.ckl
PyOKNN/data/COLUMBUS.out/.szd/w_o19nn_matrix_as_psw.ckl
PyOKNN/data/COLUMBUS.out/.szd/w_o1nn_matrix_as_arr.ckl
PyOKNN/data/COLUMBUS.out/.szd/w_o1nn_matrix_as_psw.ckl
PyOKNN/data/COLUMBUS.out/.szd/w_o20nn_matrix_as_psw.ckl
PyOKNN/data/COLUMBUS.out/.szd/w_o21nn_matrix_as_psw.ckl
PyOKNN/data/COLUMBUS.out/.szd/w_o22nn_matrix_as_arr.ckl
PyOKNN/data/COLUMBUS.out/.szd/w_o22nn_matrix_as_psw.ckl
PyOKNN/data/COLUMBUS.out/.szd/w_o23nn_matrix_as_psw.ckl
PyOKNN/data/COLUMBUS.out/.szd/w_o24nn_matrix_as_psw.ckl
PyOKNN/data/COLUMBUS.out/.szd/w_o25nn_matrix_as_psw.ckl
PyOKNN/data/COLUMBUS.out/.szd/w_o26nn_matrix_as_psw.ckl
PyOKNN/data/COLUMBUS.out/.szd/w_o27nn_matrix_as_psw.ckl
PyOKNN-0.1.66.dist-info/LICENSE
PyOKNN-0.1.66.dist-info/METADATA
PyOKNN-0.1.66.dist-info/WHEEL
PyOKNN-0.1.66.dist-info/top_level.txt
PyOKNN-0.1.66.dist-info/RECORD
