Metadata-Version: 2.1
Name: PyOKNN
Version: 0.1.66
Summary: A spatial lag operator proposal implemented in Python21: only the k-nearest neighbor (oknn), PyOKNN.
Home-page: https://github.com/lfaucheux/PyOKNN
Author: Laurent Faucheux
Author-email: laurent.faucheux@hotmail.fr
License: MIT
Download-URL: https://github.com/lfaucheux/PyOKNN/archive/0.1.66.tar.gz
Keywords: spatial econometrics,oknn specification,weight matrix
Platform: UNKNOWN
Classifier: Programming Language :: Python :: 2.7
Classifier: Intended Audience :: Developers
Classifier: Intended Audience :: Science/Research
Classifier: Topic :: Scientific/Engineering
Requires-Dist: numpy (>=1.14.0)
Requires-Dist: numdifftools (>=0.9.20)
Requires-Dist: pandas (>=0.22.0)
Requires-Dist: scipy (>=1.0.0)
Requires-Dist: pysal (>=1.14.3)
Requires-Dist: matplotlib (==1.4.3)
